mopeds/__init__.py
mopeds/casados_integrator.py
mopeds/examples.py
mopeds/model.py
mopeds/mpc.py
mopeds/optimization.py
mopeds/optimization_oed.py
mopeds/py.typed
mopeds/simulation_dynamic.py
mopeds/simulation_nle.py
mopeds/tools.py
mopeds/utilities.py
mopeds/variables.py
mopeds-0.10.2.dist-info/LICENSE.txt
mopeds-0.10.2.dist-info/METADATA
mopeds-0.10.2.dist-info/WHEEL
mopeds-0.10.2.dist-info/RECORD
