Metadata-Version: 2.3
Name: mopeds
Version: 0.10.2
Summary: Simulate and Optimize (Parameter Estimation, Optimal Experimental Design) NLE, ODE and DAE
License: MIT
Author: Volodymyr Kozachynskyi
Author-email: vovakozach@gmail.com
Requires-Python: >=3.8,<3.13
Classifier: License :: OSI Approved :: MIT License
Classifier: Programming Language :: Python :: 3
Classifier: Programming Language :: Python :: 3.8
Classifier: Programming Language :: Python :: 3.9
Classifier: Programming Language :: Python :: 3.10
Classifier: Programming Language :: Python :: 3.11
Classifier: Programming Language :: Python :: 3.12
Requires-Dist: casadi (>=3.6.4,<3.7.0)
Requires-Dist: matplotlib
Requires-Dist: numpy (<2)
Requires-Dist: pandas
Requires-Dist: scipy
Requires-Dist: tqdm
Project-URL: Homepage, https://mopeds.readthedocs.io/en/latest/
Project-URL: Repository, https://git.tu-berlin.de/dbta/optimization/mopeds
